{"type": "Feature", "id": 22656556, "geometry": {"type": "Point", "coordinates": [-0.51362, 51.58736]}, "properties": {"woe:id": 22656556, "woe:parent_id": 18076, "woe:name": "Denham Aerodrome", "woe:placetype": 14, "woe:placetype_name": "Airport", "woe:lang": "ENG", "iso:country": "GB", "meta:provider": ["geoplanet:7.3.1", "geoplanet:7.3.2", "geoplanet:7.4.0", "geoplanet:7.4.1", "geoplanet:7.5.1", "geoplanet:7.5.2", "geoplanet:7.6.0", "geoplanet:7.8.1", "geoplanet:7.9.0", "geoplanet:7.10.0", "geoplanet:8.0.0", "woeplanet:8.0.0"], "meta:indexed": "2020-08-20T19:45:17.434182", "meta:updated": "2020-10-14T11:12:20.970875", "woe:hierarchy": {"continent": 24865675, "country": 23424975, "town": 0, "planet": 1, "county": 12602166, "suburb": 0, "state": 24554868, "region": 0, "localadmin": 12695880}, "woe:timezone_id": 28350903, "woe:hash": "gcptkr1ypucj", "woe:centroid": [-0.51362, 51.58736], "geom:latitude": 51.58736, "geom:longitude": -0.51362, "geom:hash": "gcptkr1ypucj", "woe:latitude": 51.58736, "geom:centroid": [-0.51362, 51.58736], "woe:longitude": -0.51362, "woe:repo": "woeplanet-airport-gb", "geom:area": 0.0, "woe:scale": 19}}