{"type": "Feature", "id": 12518171, "properties": {"woe:id": 12518171, "woe:parent_id": 38923, "woe:name": "Waddington Airport", "woe:placetype": 14, "woe:placetype_name": "Airport", "woe:lang": "ENG", "iso:country": "GB", "meta:provider": ["geoplanet:7.3.1", "geoplanet:7.3.2", "geoplanet:7.4.0", "geoplanet:7.4.1", "geoplanet:7.5.1", "geoplanet:7.5.2", "geoplanet:7.6.0", "geoplanet:7.8.1", "geoplanet:7.9.0", "geoplanet:7.10.0", "geoplanet:8.0.0", "woeplanet:8.0.0"], "meta:indexed": "2020-08-20T19:45:17.370696", "woe:alias_ENG_V": ["WTN Airport", "WTN"], "meta:updated": "2020-08-22T02:03:19.251958", "woe:hierarchy": {"continent": 24865675, "country": 23424975, "town": 0, "planet": 1, "county": 12602145, "suburb": 0, "state": 24554868, "region": 0, "localadmin": 12696019}, "woe:timezone_id": 28350903, "woe:hash": "gcrwkne9pz56", "woe:centroid": [-0.5222, 53.165798], "geom:latitude": 53.165798, "geom:longitude": -0.5222, "geom:hash": "gcrwkne9pz56", "woe:latitude": 53.165798, "geom:centroid": [-0.5222, 53.165798], "woe:longitude": -0.5222, "woe:repo": "woeplanet-airport-gb"}, "geometry": {"coordinates": [-0.5222, 53.165798], "type": "Point"}}