{"type": "Feature", "id": 12518121, "properties": {"woe:id": 12518121, "woe:parent_id": 26771, "woe:name": "Llanbedr Airport", "woe:placetype": 14, "woe:placetype_name": "Airport", "woe:lang": "ENG", "iso:country": "GB", "meta:provider": ["geoplanet:7.3.1", "geoplanet:7.3.2", "geoplanet:7.4.0", "geoplanet:7.4.1", "geoplanet:7.5.1", "geoplanet:7.5.2", "geoplanet:7.6.0", "geoplanet:7.8.1", "geoplanet:7.9.0", "geoplanet:7.10.0", "geoplanet:8.0.0", "woeplanet:8.0.0"], "meta:indexed": "2020-08-20T19:45:17.347825", "meta:updated": "2020-08-22T02:03:19.239656", "woe:hierarchy": {"continent": 24865675, "country": 23424975, "town": 0, "planet": 1, "county": 12602221, "suburb": 0, "state": 12578049, "region": 0, "localadmin": 12696126}, "woe:timezone_id": 28350903, "woe:hash": "gcmh6nh6rw0z", "woe:centroid": [-4.1247, 52.811699], "geom:latitude": 52.811699, "geom:longitude": -4.1247, "geom:hash": "gcmh6nh6rw0z", "woe:latitude": 52.811699, "geom:centroid": [-4.1247, 52.811699], "woe:longitude": -4.1247, "woe:repo": "woeplanet-airport-gb"}, "geometry": {"coordinates": [-4.1247, 52.811699], "type": "Point"}}