{"type": "Feature", "id": 22472442, "geometry": {"type": "Point", "coordinates": [-1.62754, 59.534302]}, "properties": {"woe:id": 22472442, "woe:parent_id": 32777, "woe:name": "Fair Isle Airport", "woe:placetype": 14, "woe:placetype_name": "Airport", "woe:lang": "ENG", "iso:country": "GB", "meta:provider": ["geoplanet:7.4.0", "geoplanet:7.4.1", "geoplanet:7.5.1", "geoplanet:7.5.2", "geoplanet:7.6.0", "geoplanet:7.8.1", "geoplanet:7.9.0", "geoplanet:7.10.0", "geoplanet:8.0.0", "woeplanet:8.0.0"], "meta:indexed": "2020-08-20T23:15:48.829210", "woe:alias_ENG_V": ["FIE Airport", "FIE"], "meta:updated": "2020-10-14T11:12:20.994718", "woe:hierarchy": {"continent": 24865675, "country": 23424975, "town": 0, "planet": 1, "county": 12602205, "suburb": 0, "state": 12578048, "region": 0, "localadmin": 12696208}, "woe:timezone_id": 28350903, "woe:hash": "gfwfdvyu7w60", "woe:centroid": [-1.62754, 59.534302], "geom:latitude": 59.534302, "geom:longitude": -1.62754, "geom:hash": "gfwfdvyu7w60", "woe:latitude": 59.534302, "geom:centroid": [-1.62754, 59.534302], "woe:longitude": -1.62754, "woe:repo": "woeplanet-airport-gb", "geom:area": 0.0, "woe:scale": 19}}