{"type": "Feature", "id": 23387878, "geometry": {"type": "Point", "coordinates": [-7.64391, 54.395401]}, "properties": {"woe:id": 23387878, "woe:parent_id": 44476, "woe:name": "Enniskillen Airport", "woe:placetype": 14, "woe:placetype_name": "Airport", "woe:lang": "ENG", "iso:country": "GB", "meta:provider": ["geoplanet:7.3.1", "geoplanet:7.3.2", "geoplanet:7.4.0", "geoplanet:7.4.1", "geoplanet:7.5.1", "geoplanet:7.5.2", "geoplanet:7.6.0", "geoplanet:7.8.1", "geoplanet:7.9.0", "geoplanet:7.10.0", "geoplanet:8.0.0", "woeplanet:8.0.0"], "meta:indexed": "2020-08-20T19:45:17.474943", "woe:alias_ENG_V": ["St Angelo Airport", "ENK", "ENK Airport", "St Angelo"], "meta:updated": "2020-10-14T11:12:20.946317", "woe:hierarchy": {"continent": 24865675, "country": 23424975, "town": 0, "planet": 1, "county": 20071114, "suburb": 0, "state": 20070563, "region": 0, "localadmin": 20078335}, "woe:timezone_id": 28350903, "woe:hash": "gcdt6n3u5vxw", "woe:centroid": [-7.64391, 54.395401], "geom:latitude": 54.395401, "geom:longitude": -7.64391, "geom:hash": "gcdt6n3u5vxw", "woe:latitude": 54.395401, "geom:centroid": [-7.64391, 54.395401], "woe:longitude": -7.64391, "woe:repo": "woeplanet-airport-gb", "geom:area": 0.0, "woe:scale": 19}}