{"type": "Feature", "id": 22656550, "geometry": {"type": "Point", "coordinates": [-1.38216, 53.395679]}, "properties": {"woe:id": 22656550, "woe:parent_id": 15402, "woe:name": "Sheffield Airport", "woe:placetype": 14, "woe:placetype_name": "Airport", "woe:lang": "ENG", "iso:country": "GB", "meta:provider": ["geoplanet:7.3.1", "geoplanet:7.3.2", "geoplanet:7.4.0", "geoplanet:7.4.1", "geoplanet:7.5.1", "geoplanet:7.5.2", "geoplanet:7.6.0", "geoplanet:7.8.1", "geoplanet:7.9.0", "geoplanet:7.10.0", "geoplanet:8.0.0", "woeplanet:8.0.0"], "meta:indexed": "2020-08-20T19:45:17.428792", "woe:alias_ENG_V": ["Sheffield City Airport"], "meta:updated": "2020-10-14T11:12:20.972170", "woe:hierarchy": {"continent": 24865675, "country": 23424975, "town": 0, "planet": 1, "county": 12602196, "suburb": 0, "state": 24554868, "region": 0, "localadmin": 12695857}, "woe:timezone_id": 28350903, "woe:hash": "gcrpb83s3k4b", "woe:centroid": [-1.38216, 53.395679], "geom:latitude": 53.395679, "geom:longitude": -1.38216, "geom:hash": "gcrpb83s3k4b", "woe:latitude": 53.395679, "geom:centroid": [-1.38216, 53.395679], "woe:longitude": -1.38216, "woe:repo": "woeplanet-airport-gb", "geom:area": 0.0, "woe:scale": 19}}