{"type": "Feature", "id": 12518072, "properties": {"woe:id": 12518072, "woe:parent_id": 32850, "woe:name": "Dishforth Airport", "woe:placetype": 14, "woe:placetype_name": "Airport", "woe:lang": "ENG", "iso:country": "GB", "meta:provider": ["geoplanet:7.3.1", "geoplanet:7.3.2", "geoplanet:7.4.0", "geoplanet:7.4.1", "geoplanet:7.5.1", "geoplanet:7.5.2", "geoplanet:7.6.0", "geoplanet:7.8.1", "geoplanet:7.9.0", "geoplanet:7.10.0", "geoplanet:8.0.0", "woeplanet:8.0.0"], "meta:indexed": "2020-08-20T19:45:17.324710", "meta:updated": "2020-08-22T02:03:19.229549", "woe:hierarchy": {"continent": 24865675, "country": 23424975, "town": 0, "planet": 1, "county": 12602195, "suburb": 0, "state": 24554868, "region": 0, "localadmin": 12696045}, "woe:timezone_id": 28350903, "woe:hash": "gcwgzzbru6zy", "woe:centroid": [-1.4167, 54.140598], "geom:latitude": 54.140598, "geom:longitude": -1.4167, "geom:hash": "gcwgzzbru6zy", "woe:latitude": 54.140598, "geom:centroid": [-1.4167, 54.140598], "woe:longitude": -1.4167, "woe:repo": "woeplanet-airport-gb"}, "geometry": {"coordinates": [-1.4167, 54.140598], "type": "Point"}}