{"type": "Feature", "id": 12518065, "geometry": {"type": "Point", "coordinates": [-2.3042, 52.640301]}, "properties": {"woe:id": 12518065, "woe:parent_id": 23415615, "woe:name": "Cosford Airport", "woe:placetype": 14, "woe:placetype_name": "Airport", "woe:lang": "ENG", "iso:country": "GB", "meta:provider": ["geoplanet:7.3.1", "geoplanet:7.3.2", "geoplanet:7.4.0", "geoplanet:7.4.1", "geoplanet:7.5.1", "geoplanet:7.5.2", "geoplanet:7.6.0", "geoplanet:7.8.1", "geoplanet:7.9.0", "geoplanet:7.10.0", "geoplanet:8.0.0", "woeplanet:8.0.0"], "meta:indexed": "2020-08-20T19:45:17.321172", "meta:updated": "2020-10-14T11:12:21.025076", "woe:hierarchy": {"continent": 24865675, "country": 23424975, "town": 0, "planet": 1, "county": 12602188, "suburb": 0, "state": 24554868, "region": 0, "localadmin": 12696062}, "woe:timezone_id": 28350903, "woe:hash": "gcq77wf5uprf", "woe:centroid": [-2.3042, 52.640301], "geom:latitude": 52.640301, "geom:longitude": -2.3042, "geom:hash": "gcq77wf5uprf", "woe:latitude": 52.640301, "geom:centroid": [-2.3042, 52.640301], "woe:longitude": -2.3042, "woe:repo": "woeplanet-airport-gb", "geom:area": 0.0, "woe:scale": 19}}