{"type": "Feature", "id": 22492354, "properties": {"woe:id": 22492354, "woe:parent_id": 17542, "woe:name": "Humberside International Airport", "woe:placetype": 14, "woe:placetype_name": "Airport", "woe:lang": "ENG", "iso:country": "GB", "meta:provider": ["geoplanet:7.4.0", "geoplanet:7.4.1", "geoplanet:7.5.1", "geoplanet:7.5.2", "geoplanet:7.6.0", "geoplanet:7.8.1", "geoplanet:7.9.0", "geoplanet:7.10.0", "geoplanet:8.0.0", "woeplanet:8.0.0"], "meta:indexed": "2020-08-20T23:15:48.835027", "woe:alias_DAN_Q": ["Humberside Lufthavn"], "woe:alias_ENG_V": ["Humberside", "Humberside International", "HUY Airport", "HUY", "Humberside Airport"], "woe:alias_FIN_S": ["Humberside Lentokentta"], "woe:alias_FRE_Q": ["A\u00e8roport de Humberside"], "woe:alias_FIN_Q": ["Humberside Lentokentt\u00e4"], "woe:alias_SWE_Q": ["Humberside Flygplats"], "woe:alias_UNK_Q": ["Letiste Humberside", "Letisko Humberside"], "woe:alias_DUT_Q": ["Luchthaven Humberside"], "woe:alias_GER_Q": ["Flughafen Humberside"], "meta:updated": "2020-08-22T02:03:19.274249", "woe:alias_ITA_Q": ["Aeroporto Di Humberside"], "woe:alias_SPA_Q": ["Aeropuerto de Humberside"], "woe:alias_FRE_S": ["Aeroport de Humberside"], "woe:alias_POR_Q": ["Aeroporto de Humberside"], "woe:alias_FIN_V": ["Humbersiden Lentoasema"], "woe:alias_HUN_V": ["Humberside-I Rep\u00fcl\u0151t\u00e9r", "Humberside-I Repuloter"], "woe:alias_FRE_V": ["A\u00e9roport de Humberside"], "woe:alias_POL_V": ["Port Lotniczy Humberside"], "woe:alias_CZE_V": ["Leti\u0161t\u011b Humberside"], "woe:alias_UNK_V": ["\u0391\u03b5\u03c1\u03bf\u03b4\u03c1\u03bf\u03bc\u03b9\u03bf \u03a7\u03b1\u03bc\u03c0\u03b5\u03c1\u03c3\u03b1\u03ca\u03bd\u03c4", "\u0391\u03b5\u03c1\u03bf\u03b4\u03c1\u03bfmu\u03b9\u03bf \u03a7\u03b1mu\u03c0\u03b5\u03c1\u03c3\u03b1\u03b9\u03bd\u03c4", "\u0410\u044d\u0440\u043e\u043f\u043e\u0440\u0442 \u0425\u0430\u043c\u0431\u0435\u0440\u0441\u0430\u0439\u0434", "\u0410\u044d\u0440\u043e\u043f\u043e\u0440\u0442 \u0425\u0430\u043c\u0431\u0435\u0440\u0441\u0430\u0438\u0434"], "woe:hierarchy": {"continent": 24865675, "country": 23424975, "town": 0, "planet": 1, "county": 12602145, "suburb": 0, "state": 24554868, "region": 0, "localadmin": 12696143}, "woe:timezone_id": 28350903, "woe:hash": "gcxbb4d49tcn", "woe:centroid": [-0.34875, 53.58353], "geom:latitude": 53.58353, "geom:longitude": -0.34875, "geom:hash": "gcxbb4d49tcn", "woe:latitude": 53.58353, "geom:centroid": [-0.34875, 53.58353], "woe:longitude": -0.34875, "woe:repo": "woeplanet-airport-gb"}, "geometry": {"coordinates": [-0.34875, 53.58353], "type": "Point"}}