{"type": "Feature", "id": 12523978, "properties": {"woe:id": 12523978, "woe:parent_id": 16122, "woe:name": "Coll Island Airport", "woe:placetype": 14, "woe:placetype_name": "Airport", "woe:lang": "ENG", "iso:country": "GB", "meta:provider": ["geoplanet:7.3.1", "geoplanet:7.3.2", "geoplanet:7.4.0", "geoplanet:7.4.1", "geoplanet:7.5.1", "geoplanet:7.5.2", "geoplanet:7.6.0", "geoplanet:7.8.1", "geoplanet:7.9.0", "geoplanet:7.10.0", "geoplanet:8.0.0", "woeplanet:8.0.0"], "meta:indexed": "2020-08-20T19:45:17.383246", "woe:alias_ENG_V": ["COL Airport", "COL"], "meta:updated": "2020-08-22T02:03:19.258358", "woe:hierarchy": {"continent": 24865675, "country": 23424975, "town": 0, "planet": 1, "county": 12602207, "suburb": 0, "state": 12578048, "region": 0, "localadmin": 12696185}, "woe:timezone_id": 28350903, "woe:hash": "gf5616vbhmtk", "woe:centroid": [-6.61667, 56.616699], "geom:latitude": 56.616699, "geom:longitude": -6.61667, "geom:hash": "gf5616vbhmtk", "woe:latitude": 56.616699, "geom:centroid": [-6.61667, 56.616699], "woe:longitude": -6.61667, "woe:repo": "woeplanet-airport-gb"}, "geometry": {"coordinates": [-6.61667, 56.616699], "type": "Point"}}