{"type": "Feature", "id": 12518106, "geometry": {"type": "Point", "coordinates": [-2.055, 51.668098]}, "properties": {"woe:id": 12518106, "woe:parent_id": 15795, "woe:name": "Kemble Airport", "woe:placetype": 14, "woe:placetype_name": "Airport", "woe:lang": "ENG", "iso:country": "GB", "meta:provider": ["geoplanet:7.3.1", "geoplanet:7.3.2", "geoplanet:7.4.0", "geoplanet:7.4.1", "geoplanet:7.5.1", "geoplanet:7.5.2", "geoplanet:7.6.0", "geoplanet:7.8.1", "geoplanet:7.9.0", "geoplanet:7.10.0", "geoplanet:8.0.0", "woeplanet:8.0.0"], "meta:indexed": "2020-08-20T19:45:17.340068", "meta:updated": "2020-10-14T11:12:21.085729", "woe:hierarchy": {"continent": 24865675, "country": 23424975, "town": 0, "planet": 1, "county": 12602186, "suburb": 0, "state": 24554868, "region": 0, "localadmin": 12696111}, "woe:timezone_id": 28350903, "woe:hash": "gcntcjzs7p8c", "woe:centroid": [-2.055, 51.668098], "geom:latitude": 51.668098, "geom:longitude": -2.055, "geom:hash": "gcntcjzs7p8c", "woe:latitude": 51.668098, "geom:centroid": [-2.055, 51.668098], "woe:longitude": -2.055, "woe:repo": "woeplanet-airport-gb", "geom:area": 0.0, "woe:scale": 19}}